curverunner/__init__.py
curverunner/comm.py
curverunner/curverunner.py
curverunner/py.typed
curverunner/util.py
curverunner/version.py
curverunner-0.2.0.dist-info/licenses/LICENSE
examples/hello_curverunner.py
examples/motor_control_percent_out.py
examples/update_device_id.py
curverunner-0.2.0.dist-info/METADATA
curverunner-0.2.0.dist-info/WHEEL
curverunner-0.2.0.dist-info/top_level.txt
curverunner-0.2.0.dist-info/RECORD
