Metadata-Version: 2.4
Name: curverunner
Version: 0.2.0
Summary: Python library for interfacing with the Curverunner motor controller.
Author-email: Connor Belli <connorbelli2003@gmail.com>
License:                                  Apache License
Project-URL: Homepage, https://github.com/connor-belli/curverunner-python
Project-URL: Repository, https://github.com/connor-belli/curverunner-python
Project-URL: Changelog, https://github.com/connor-belli/curverunner-python/blob/main/CHANGELOG.md
Classifier: Intended Audience :: Science/Research
Classifier: Development Status :: 3 - Alpha
Classifier: License :: OSI Approved :: Apache Software License
Classifier: Programming Language :: Python :: 3
Classifier: Topic :: Scientific/Engineering
Classifier: Topic :: System :: Hardware
Requires-Python: >=3.8
License-File: LICENSE
Requires-Dist: pyserial>=3.5
Requires-Dist: smbus2>=0.5
Provides-Extra: dev
Requires-Dist: ruff; extra == "dev"
Requires-Dist: mypy<2.0,>=1.0; extra == "dev"
Requires-Dist: black<25.0,>=23.0; extra == "dev"
Requires-Dist: isort<5.14,>=5.12; extra == "dev"
Requires-Dist: pytest; extra == "dev"
Requires-Dist: pytest-sphinx; extra == "dev"
Requires-Dist: pytest-cov; extra == "dev"
Requires-Dist: twine>=1.11.0; extra == "dev"
Requires-Dist: build; extra == "dev"
Requires-Dist: setuptools; extra == "dev"
Requires-Dist: wheel; extra == "dev"
Requires-Dist: Sphinx<9.0,>=6.0; extra == "dev"
Requires-Dist: furo==2024.8.6; extra == "dev"
Requires-Dist: myst-parser>=1.0; extra == "dev"
Requires-Dist: sphinx-copybutton; extra == "dev"
Requires-Dist: sphinx-autobuild; extra == "dev"
Requires-Dist: sphinx-autodoc-typehints==1.23.3; extra == "dev"
Requires-Dist: packaging; extra == "dev"
Dynamic: license-file
